naics.py
naics-1.0.1.dist-info/METADATA
naics-1.0.1.dist-info/WHEEL
naics-1.0.1.dist-info/top_level.txt
naics-1.0.1.dist-info/RECORD
